codebaselister/__init__.py
codebaselister/main.py
CodebaseLister-0.0.2.dist-info/LICENSE
CodebaseLister-0.0.2.dist-info/METADATA
CodebaseLister-0.0.2.dist-info/WHEEL
CodebaseLister-0.0.2.dist-info/top_level.txt
CodebaseLister-0.0.2.dist-info/RECORD
