Metadata-Version: 2.1
Name: CodebaseLister
Version: 0.0.2
Summary: A package to list and document the contents of codebases, optionally using .gitignore rules.
Home-page: https://github.com/chigwell/CodebaseLister
Author: Eugene Evstafev
Author-email: chigwel@gmail.com
License: UNKNOWN
Platform: UNKNOWN
Classifier: Programming Language :: Python :: 3
Classifier: License :: OSI Approved :: MIT License
Classifier: Operating System :: OS Independent
Requires-Python: >=3.6
Requires-Dist: pathspec
